{
  "_class": "bitmap",
  "clippingMask": "{{0, 0}, {1, 1}}",
  "do_objectID": "6B67225E-64AE-4D53-8595-B3D90C634EDE",
  "exportOptions": {
    "_class": "exportOptions",
    "exportFormats": [
    ],
    "includedLayerIds": [
    ],
    "layerOptions": 0,
    "shouldTrim": false
  },
  "fillReplacesImage": false,
  "frame": {
    "_class": "rect",
    "constrainProportions": true,
    "height": 82,
    "width": 215,
    "x": 0,
    "y": 0
  },
  "image": {
    "_class": "MSJSONFileReference",
    "_ref": "images/14742d4ce9c4b2cccc645d9feeaf46046a31f662",
    "_ref_class": "MSImageData"
  },
  "isFlippedHorizontal": false,
  "isFlippedVertical": false,
  "isLocked": false,
  "isVisible": true,
  "layerListExpandedType": 0,
  "name": "Screenshot 2017-09-24 16.53.45",
  "nameIsFixed": false,
  "nineSliceCenterRect": "{{0, 0}, {0, 0}}",
  "nineSliceScale": "{0, 0}",
  "resizingConstraint": 63,
  "resizingType": 0,
  "rotation": 0,
  "shouldBreakMaskChain": false,
  "style": {
    "_class": "style",
    "endDecorationType": 0,
    "miterLimit": 10,
    "startDecorationType": 0
  },
  "userInfo": {
    "com.animaapp.stc-sketch-plugin": {
      "kModelPropertiesKey": {
      }
    }
  }
}